README.rst
setup.py
serve_me_do/__init__.py
serve_me_do.egg-info/PKG-INFO
serve_me_do.egg-info/SOURCES.txt
serve_me_do.egg-info/dependency_links.txt
serve_me_do.egg-info/entry_points.txt
serve_me_do.egg-info/top_level.txt