Metadata-Version: 1.0
Name: serve-me-do
Version: 0.0.2
Summary: command to serve some directory with multithreaded http server
Home-page: http://github.com/felipelerena/serve_me_do/
Author: Felipe Lerena
Author-email: felipelerena@gmail.com
License: WTFPL
Platform: UNKNOWN
